LICENSE
MANIFEST.in
README.md
pyproject.toml
setup.py
walnutpi_npu/NPU.py
walnutpi_npu/YOLO11.py
walnutpi_npu/__init__.py
walnutpi_npu.egg-info/PKG-INFO
walnutpi_npu.egg-info/SOURCES.txt
walnutpi_npu.egg-info/dependency_links.txt
walnutpi_npu.egg-info/requires.txt
walnutpi_npu.egg-info/top_level.txt
walnutpi_npu/_awnn_lib/libawnn_t527.so
walnutpi_npu/_awnn_lib/py_awnn_lib.c
walnutpi_npu/_awnn_lib/t527/Makefile
walnutpi_npu/_awnn_lib/t527/libawnn_t527.so
walnutpi_npu/_awnn_lib/t527/header/awnn_internal.h
walnutpi_npu/_awnn_lib/t527/header/awnn_lib.h
walnutpi_npu/_awnn_lib/t527/header/awnn_quantize.h
walnutpi_npu/_awnn_lib/t527/header/vip_lite.h
walnutpi_npu/_awnn_lib/t527/header/vip_lite_common.h
walnutpi_npu/_awnn_lib/t527/lib/libVIPlite.so
walnutpi_npu/_awnn_lib/t527/lib/libVIPuser.so
walnutpi_npu/_awnn_lib/t527/src/awnn_lib.c
walnutpi_npu/_awnn_lib/t527/src/awnn_lib.o
walnutpi_npu/_awnn_lib/t527/src/awnn_quantize.c
walnutpi_npu/_awnn_lib/t527/src/awnn_quantize.o