Metadata-Version: 2.4
Name: walnutpi_npu
Version: 0.0.9
Summary: A module to control npu on T-527
Author-email: sc-bin <3335447573@qq.com>
License-Expression: MIT
Project-URL: Homepage, https://github.com/sc-bin/
Classifier: Development Status :: 3 - Alpha
Classifier: Intended Audience :: Developers
Classifier: Topic :: Software Development :: Build Tools
Classifier: Programming Language :: Python :: 3
License-File: LICENSE
Requires-Dist: numpy
Requires-Dist: opencv-contrib-python
Dynamic: license-file
